{
  "userIsCoordinator": true,
  "sections": {
    "{Monday}": [
      {
        "id": 1,
        "spacetimes": [
          {
            "startTime": "11:00:00",
            "dayOfWeek": "Monday",
            "time": "Monday 11:00 AM-12:00 PM",
            "location": "Cory 400",
            "id": 123,
            "duration": "01:00:00",
            "override": null
          }
        ],
        "mentor": {
          "id": 1001,
          "name": "Test Mentor 1",
          "email": "test_mentor_1@berkeley.edu",
          "section": 1
        },
        "capacity": 5,
        "associatedProfileId": null,
        "numStudentsEnrolled": 3,
        "description": "Affinity section",
        "course": "CS61A",
        "userRole": null,
        "courseTitle": "Structure and Interpretation of Computer Programs"
      },
      {
        "id": 2,
        "spacetimes": [
          {
            "startTime": "12:00:00",
            "dayOfWeek": "Monday",
            "time": "Monday 12:00-11:30 PM",
            "location": "Cory 300",
            "id": 1234,
            "duration": "01:30:00",
            "override": null
          }
        ],
        "mentor": {
          "id": 1002,
          "name": "Test Mentor 2",
          "email": "test_mentor_2@berkeley.edu",
          "section": 2
        },
        "capacity": 3,
        "associatedProfileId": null,
        "numStudentsEnrolled": 3,
        "description": "",
        "course": "CS61A",
        "userRole": null,
        "courseTitle": "Structure and Interpretation of Computer Programs"
      },
      {
        "id": 3,
        "spacetimes": [
          {
            "startTime": "16:00:00",
            "dayOfWeek": "Monday",
            "time": "Monday 4:00-5:00 PM",
            "location": "Soda 380",
            "id": 12345,
            "duration": "01:00:00",
            "override": null
          }
        ],
        "mentor": {
          "id": 1003,
          "name": "Test Mentor 3",
          "email": "test_mentor_3@berkeley.edu",
          "section": 3
        },
        "capacity": 4,
        "associatedProfileId": null,
        "numStudentsEnrolled": 0,
        "description": "description",
        "course": "CS61A",
        "userRole": null,
        "courseTitle": "Structure and Interpretation of Computer Programs"
      }
    ],
    "{Tuesday,Wednesday}": [
      {
        "id": 4,
        "spacetimes": [
          {
            "startTime": "16:00:00",
            "dayOfWeek": "Tuesday",
            "time": "Tuesday 4:00-5:00 PM",
            "location": "Cory 212",
            "id": 124,
            "duration": "01:00:00",
            "override": null
          },
          {
            "startTime": "16:00:00",
            "dayOfWeek": "Wednesday",
            "time": "Wednesday 4:00-5:00 PM",
            "location": "Cory 400",
            "id": 125,
            "duration": "01:00:00",
            "override": null
          }
        ],
        "mentor": {
          "id": 1004,
          "name": "Test Mentor 4",
          "email": "test_mentor_4@berkeley.edu",
          "section": 4
        },
        "capacity": 3,
        "associatedProfileId": null,
        "numStudentsEnrolled": 0,
        "description": "Online",
        "course": "CS61A",
        "userRole": null,
        "courseTitle": "Structure and Interpretation of Computer Programs"
      },
      {
        "id": 5,
        "spacetimes": [
          {
            "startTime": "11:00:00",
            "dayOfWeek": "Tuesday",
            "time": "Tuesday 11:00 AM-12:30 PM",
            "location": "Cory 212",
            "id": 224,
            "duration": "01:30:00",
            "override": null
          },
          {
            "startTime": "12:00:00",
            "dayOfWeek": "Wednesday",
            "time": "Wednesday 12:00-1:00 PM",
            "location": "Soda 286",
            "id": 225,
            "duration": "01:00:00",
            "override": null
          }
        ],
        "mentor": {
          "id": 1005,
          "name": "Test Mentor 5",
          "email": "test_mentor_5@berkeley.edu",
          "section": 5
        },
        "capacity": 4,
        "associatedProfileId": null,
        "numStudentsEnrolled": 4,
        "description": "Online",
        "course": "CS61A",
        "userRole": null,
        "courseTitle": "Structure and Interpretation of Computer Programs"
      }
    ],
    "{Thursday}": [
      {
        "id": 6,
        "spacetimes": [
          {
            "startTime": "13:00:00",
            "dayOfWeek": "Thursday",
            "time": "Thursday 1:00-2:00 PM",
            "location": "Soda 300",
            "id": 15,
            "duration": "01:00:00",
            "override": null
          }
        ],
        "mentor": {
          "id": 1006,
          "name": "Test Mentor 6",
          "email": "test_mentor_6@berkeley.edu",
          "section": 6
        },
        "capacity": 3,
        "associatedProfileId": null,
        "numStudentsEnrolled": 3,
        "description": "",
        "course": "CS61A",
        "userRole": null,
        "courseTitle": "Structure and Interpretation of Computer Programs"
      }
    ]
  }
}
